dagster_omni/__init__.py
dagster_omni/component.py
dagster_omni/objects.py
dagster_omni/py.typed
dagster_omni/translation.py
dagster_omni/version.py
dagster_omni/workspace.py
dagster_omni-0.28.13.dist-info/licenses/LICENSE
dagster_omni-0.28.13.dist-info/METADATA
dagster_omni-0.28.13.dist-info/WHEEL
dagster_omni-0.28.13.dist-info/top_level.txt
dagster_omni-0.28.13.dist-info/RECORD
